pyproject.toml
src/learning_curve_projects/__init__.py
src/learning_curve_projects/core.py
src/learning_curve_projects.egg-info/PKG-INFO
src/learning_curve_projects.egg-info/SOURCES.txt
src/learning_curve_projects.egg-info/dependency_links.txt
src/learning_curve_projects.egg-info/requires.txt
src/learning_curve_projects.egg-info/top_level.txt