Metadata-Version: 2.4
Name: learning-curve-projects
Version: 0.0.1
Summary: Learning curve projects
Requires-Python: >=3.9
Requires-Dist: pycryptodome
Requires-Dist: requests
